{
  "source_file": "data\\processed\\01_illumination_normalized\\IMG_0507.png",
  "overlay_file": "data\\processed\\06_boot_landmarks\\circles_overlay\\IMG_0507.png",
  "input_mode": "edges",
  "width": 3024,
  "height": 4032,
  "processing_step": "06_detect_boot_landmarks",
  "nonzero_before": 63131,
  "nonzero_hough": 63131,
  "hough_parameters": {
    "dp": 1.1,
    "min_dist": 45.0,
    "param1": 100.0,
    "param2": 75.0,
    "min_radius": 12,
    "max_radius": 75
  },
  "circle_count": 3,
  "circles": [
    {
      "id": 1,
      "x": 1438,
      "y": 1653,
      "radius": 51
    },
    {
      "id": 2,
      "x": 1761,
      "y": 1530,
      "radius": 50
    },
    {
      "id": 3,
      "x": 1442,
      "y": 1171,
      "radius": 32
    }
  ]
}